KanvasObjectKlick/__init__.py
KanvasObjectKlick/assets.py
KanvasObjectKlick/common.py
KanvasObjectKlick/process.py
kanvasobjectklick-0.2.0.dist-info/licenses/LICENSE
kanvasobjectklick-0.2.0.dist-info/METADATA
kanvasobjectklick-0.2.0.dist-info/WHEEL
kanvasobjectklick-0.2.0.dist-info/top_level.txt
kanvasobjectklick-0.2.0.dist-info/RECORD
