Metadata-Version: 2.4
Name: KanvasObjectKlick
Version: 0.2.0
Summary: Allows you to visualize objects with html on a 2D canvas with the desired color, caption (on hover), and image of the object (on click). 
Author-email: The220th <The220th@gmail.com>
Project-URL: Homepage, https://github.com/The220th/KanvasObjectKlick
Project-URL: Issues, https://github.com/The220th/KanvasObjectKlick/issues
Classifier: Programming Language :: Python :: 3
Classifier: License :: OSI Approved :: MIT License
Classifier: Operating System :: OS Independent
Requires-Python: >=3.7
License-File: LICENSE
Requires-Dist: pillow
Requires-Dist: ksupk
Requires-Dist: numpy
Dynamic: license-file
